{
  "meta": {
    "repo": "uhafner/codingstyle-pom",
    "stage": "J17->J21",
    "family": "junit4-mockito",
    "sha_from": "94b2db24585383bc1adac14c22a852c2b2de8087",
    "sha_to": "d477571b0419bb247b909e02ab3ee34f2d265641"
  },
  "by_file": {
    "pom.xml": [
      {
        "kind": "bump_jdk_version",
        "general_idea": "Update the minimum required Java version from 17 to 21 to align with the target runtime.",
        "human_impl": "<java.version>21</java.version>",
        "bucket": "breaking"
      },
      {
        "kind": "migrate_publishing_plugin",
        "general_idea": "Replace the deprecated Nexus Staging Maven Plugin with the new Central Publishing Maven Plugin for Maven Central deployment.",
        "human_impl": "<artifactId>central-publishing-maven-plugin</artifactId>",
        "bucket": "breaking"
      },
      {
        "kind": "update_compiler_lint_args",
        "general_idea": "Adjust compiler arguments to enable all lints and suppress specific warnings relevant to Java 21 module system and Error Prone integration.",
        "human_impl": "<arg>-Xlint:all</arg> ... <arg>--should-stop=ifError=FLOW</arg>",
        "bucket": "polishment"
      },
      {
        "kind": "update_rewrite_recipes",
        "general_idea": "Update OpenRewrite recipes to target Java 21 migration patterns instead of Java 17.",
        "human_impl": "<recipe>org.openrewrite.java.migrate.UpgradeToJava21</recipe>",
        "bucket": "polishment"
      },
      {
        "kind": "enable_pitmute",
        "general_idea": "Enable PitMute feature in Pitest to suppress known mutations using a CSV file.",
        "human_impl": "<feature>+FCSV(csvFile[etc/pitmute.csv]) allowMissingFile[true])</feature>",
        "bucket": "polishment"
      },
      {
        "kind": "add_pmd_metrics",
        "general_idea": "Add a new PMD execution to generate code metrics using the custom metrics renderer.",
        "human_impl": "<id>run-pmd-metrics</id> ... <format>net.sourceforge.pmd.renderers.MetricsRenderer</format>",
        "bucket": "polishment"
      },
      {
        "kind": "refactor_surefire_executions",
        "general_idea": "Split Surefire executions to separate standard tests from ArchUnit architecture tests for better reporting.",
        "human_impl": "<id>architecture-test</id> ... <include>**/archunit/**</include>",
        "bucket": "polishment"
      },
      {
        "kind": "update_error_prone_config",
        "general_idea": "Update Error Prone configuration to disable specific rules and adjust warning levels for the new version.",
        "human_impl": "<arg>-Xep:SuppressWarningsWithoutExplanation:OFF</arg>",
        "bucket": "polishment"
      },
      {
        "kind": "update_revapi_config",
        "general_idea": "Update RevAPI configuration to handle SpotBugs annotations and improve JSON report formatting.",
        "human_impl": "<code>java.annotation.removed</code> ... <indent>true</indent>",
        "bucket": "polishment"
      },
      {
        "kind": "update_dependency_versions",
        "general_idea": "Bump versions of various dependencies (JUnit, Mockito, Checkstyle, etc.) to their latest compatible releases.",
        "human_impl": "<junit.version>6.0.2</junit.version> ... <checkstyle.version>13.0.0</checkstyle.version>",
        "bucket": "polishment"
      },
      {
        "kind": "update_plugin_versions",
        "general_idea": "Bump versions of Maven plugins (Compiler, Javadoc, PMD, etc.) to their latest releases.",
        "human_impl": "<maven-compiler-plugin.version>3.14.1</maven-compiler-plugin.version> ... <pmd.version>7.20.0</pmd.version>",
        "bucket": "polishment"
      },
      {
        "kind": "add_dependency_plugin_properties",
        "general_idea": "Add maven-dependency-plugin execution to expose dependency versions as properties for use in other plugins.",
        "human_impl": "<goal>properties</goal>",
        "bucket": "polishment"
      },
      {
        "kind": "update_pmd_dependencies",
        "general_idea": "Switch PMD core and Java dependencies to the custom metrics-enabled versions.",
        "human_impl": "<groupId>edu.hm.hafner</groupId> ... <version>${pmd.metrics.version}</version>",
        "bucket": "polishment"
      },
      {
        "kind": "update_dependency_check_config",
        "general_idea": "Update OWASP Dependency-Check configuration to include OSS Index credentials and adjust format.",
        "human_impl": "<ossIndexUsername>ullrich.hafner@gmail.com</ossIndexUsername>",
        "bucket": "polishment"
      },
      {
        "kind": "update_release_plugin_config",
        "general_idea": "Configure maven-release-plugin commit messages to include skip CI tags.",
        "human_impl": "<scmDevelopmentCommitComment>@{prefix} Prepare for next development iteration [skip ci]</scmDevelopmentCommitComment>",
        "bucket": "polishment"
      },
      {
        "kind": "update_sortpom_config",
        "general_idea": "Enable sorting of dependency exclusions in sortpom plugin configuration.",
        "human_impl": "<sortDependencyExclusions>groupId,artifactId</sortDependencyExclusions>",
        "bucket": "polishment"
      },
      {
        "kind": "update_assertj_templates",
        "general_idea": "Add new template configurations for AssertJ assertions generator plugin.",
        "human_impl": "<assertionEntryPointMethod>assertions_entry_point_method_template.txt</assertionEntryPointMethod>",
        "bucket": "polishment"
      },
      {
        "kind": "add_build_helper_plugin",
        "general_idea": "Add build-helper-maven-plugin to plugin management for potential future use.",
        "human_impl": "<artifactId>build-helper-maven-plugin</artifactId>",
        "bucket": "polishment"
      },
      {
        "kind": "add_versions_plugin",
        "general_idea": "Add versions-maven-plugin to plugin management for dependency version management.",
        "human_impl": "<artifactId>versions-maven-plugin</artifactId>",
        "bucket": "polishment"
      },
      {
        "kind": "update_pmd_print_failing_errors",
        "general_idea": "Enable printing of failing errors in PMD executions for better visibility.",
        "human_impl": "<printFailingErrors>true</printFailingErrors>",
        "bucket": "polishment"
      },
      {
        "kind": "update_pmd_source_roots",
        "general_idea": "Update PMD JavaScript source roots to use project.basedir instead of basedir.",
        "human_impl": "<compileSourceRoot>${project.basedir}/src/main/resources</compileSourceRoot>",
        "bucket": "polishment"
      },
      {
        "kind": "update_revapi_fail_build",
        "general_idea": "Disable failing the build on RevAPI problems in the development profile.",
        "human_impl": "<revapi.failBuildOnProblemsFound>false</revapi.failBuildOnProblemsFound>",
        "bucket": "polishment"
      },
      {
        "kind": "update_surefire_argline",
        "general_idea": "Update Surefire argLine to include logging config and Mockito agent.",
        "human_impl": "<argLine>@{argLine} -Djava.util.logging.config.file=logging.properties -javaagent:${org.mockito:mockito-core:jar}</argLine>",
        "bucket": "polishment"
      },
      {
        "kind": "update_failsafe_argline",
        "general_idea": "Update Failsafe argLine to include logging config and Mockito agent.",
        "human_impl": "<argLine>@{argLine} -Djava.util.logging.config.file=logging.properties -javaagent:${org.mockito:mockito-core:jar}</argLine>",
        "bucket": "polishment"
      },
      {
        "kind": "update_enforcer_java_version",
        "general_idea": "Update maven-enforcer-plugin to require the build version of Java instead of a hardcoded version.",
        "human_impl": "<version>${java.build.version}</version>",
        "bucket": "polishment"
      },
      {
        "kind": "remove_distribution_management",
        "general_idea": "Remove explicit distribution management configuration as it is handled by the new central publishing plugin.",
        "human_impl": "<!-- removed distributionManagement block -->",
        "bucket": "polishment"
      },
      {
        "kind": "update_spotbugs_exclusions",
        "general_idea": "Remove unnecessary exclusion of jsr305 from spotbugs-annotations.",
        "human_impl": "<!-- removed exclusions block from spotbugs-annotations -->",
        "bucket": "polishment"
      },
      {
        "kind": "update_equalsverifier_exclusions",
        "general_idea": "Add exclusion for junit-platform-engine in equalsverifier dependency.",
        "human_impl": "<exclusion> <groupId>org.junit.platform</groupId> <artifactId>junit-platform-engine</artifactId> </exclusion>",
        "bucket": "polishment"
      },
      {
        "kind": "update_codingstyle_version",
        "general_idea": "Bump the internal codingstyle configuration and library versions.",
        "human_impl": "<codingstyle.config.version>5.27.0</codingstyle.config.version>",
        "bucket": "polishment"
      },
      {
        "kind": "update_project_version",
        "general_idea": "Bump the project version to 6.0.0-SNAPSHOT.",
        "human_impl": "<version>6.0.0-SNAPSHOT</version>",
        "bucket": "polishment"
      },
      {
        "kind": "update_description_text",
        "general_idea": "Minor text updates in the project description.",
        "human_impl": "\u2014 I am using this coding style ... as the parent of your own POM",
        "bucket": "polishment"
      }
    ],
    ".github/auto_assign.yml": [
      {
        "kind": "switch_auto_assign_to_reviewers",
        "general_idea": "Change the GitHub auto-assign configuration to add reviewers instead of assignees for pull requests.",
        "human_impl": "addReviewers: true\naddAssignees: false\nreviewers:\n  - uhafner\nnumberOfReviewers: 0",
        "bucket": "polishment"
      }
    ],
    ".github/dependabot.yml": [
      {
        "kind": "remove_dependency_ignore",
        "general_idea": "Remove the version ignore rule for json-unit-assertj to allow Dependabot to update it to newer versions.",
        "human_impl": "-      - dependency-name: net.javacrumbs.json-unit:json-unit-assertj\n-        versions:\n-          - \">= 3.0.0\"",
        "bucket": "polishment"
      },
      {
        "kind": "add_dependency_ignore",
        "general_idea": "Add ignore rules for datatables.net-responsive and datatables.net-responsive-bs5 to prevent Dependabot from updating them beyond version 3.0.2.",
        "human_impl": "+    ignore:\n+      - dependency-name: datatables.net-responsive\n+        versions:\n+          - \"> 3.0.2\"\n+      - dependency-name: datatables.net-responsive-bs5\n+        versions:\n+          - \"> 3.0.2\"",
        "bucket": "polishment"
      }
    ],
    ".github/workflows/check-md-links.yml": [
      {
        "kind": "update_action_version",
        "general_idea": "Bump the checkout action to a newer major version.",
        "human_impl": "- uses: actions/checkout@v4\n+ uses: actions/checkout@v6",
        "bucket": "polishment"
      },
      {
        "kind": "replace_link_checker",
        "general_idea": "Replace the markdown link checking action with a different tool (linkspector).",
        "human_impl": "- uses: gaurav-nelson/github-action-markdown-link-check@v1\n+ uses: umbrelladocs/action-linkspector@v1.4.0",
        "bucket": "polishment"
      },
      {
        "kind": "update_link_checker_config",
        "general_idea": "Update configuration parameters to match the new link checker tool's requirements.",
        "human_impl": "- check-modified-files-only: 'no'\n- config-file: '.github/check-md-links.json'\n+ github_token: ${{ secrets.github_token }}\n+ reporter: github-pr-check\n+ fail_on_error: true\n+ filter_mode: nofilter\n+ config_file: '.github/linkspector.yml'\n+ level: 'info'",
        "bucket": "polishment"
      }
    ],
    ".github/workflows/ci.yml": [
      {
        "kind": "update_jdk_matrix",
        "general_idea": "Update the CI matrix to test against JDK 21 and 25, removing JDK 17 to align with the new minimum version requirement.",
        "human_impl": "jdk: [21, 25]",
        "bucket": "breaking"
      },
      {
        "kind": "add_fail_fast_false",
        "general_idea": "Disable fail-fast in the CI strategy to allow all matrix combinations to complete even if one fails.",
        "human_impl": "fail-fast: false",
        "bucket": "polishment"
      },
      {
        "kind": "bump_checkout_action",
        "general_idea": "Upgrade the GitHub Actions checkout action from version 4 to version 6.",
        "human_impl": "uses: actions/checkout@v6",
        "bucket": "polishment"
      },
      {
        "kind": "bump_setup_java_action",
        "general_idea": "Upgrade the GitHub Actions setup-java action from version 4 to version 5.",
        "human_impl": "uses: actions/setup-java@v5",
        "bucket": "polishment"
      },
      {
        "kind": "bump_maven_version",
        "general_idea": "Update the Maven version used in CI from 3.9.9 to 3.9.11.",
        "human_impl": "maven-version: 3.9.11",
        "bucket": "polishment"
      },
      {
        "kind": "add_ci_profile",
        "general_idea": "Add the 'ci' Maven profile to the build command to enable CI-specific configurations.",
        "human_impl": "run: mvn ... -Pci ...",
        "bucket": "polishment"
      },
      {
        "kind": "add_no_ui_tests_profile",
        "general_idea": "Add the 'no-ui-tests' Maven profile to the build command to skip UI tests in CI.",
        "human_impl": "run: mvn ... -Pno-ui-tests ...",
        "bucket": "polishment"
      }
    ],
    ".github/workflows/enforce-labels.yml": [
      {
        "kind": "change_github_trigger_event",
        "general_idea": "Switch the workflow trigger from pull_request to pull_request_target to allow the workflow to run with permissions of the target repository.",
        "human_impl": "pull_request_target:",
        "bucket": "polishment"
      }
    ],
    ".github/workflows/run-release-drafter.yml": [
      {
        "kind": "bump_github_action_version",
        "general_idea": "Update the release-drafter GitHub Action to version 6.1.0.",
        "human_impl": "- uses: release-drafter/release-drafter@v6.0.0\n+ uses: release-drafter/release-drafter@v6.1.0",
        "bucket": "polishment"
      }
    ],
    ".github/workflows/sync-labels.yml": [
      {
        "kind": "bump_github_action_checkout",
        "general_idea": "Update the checkout action to a newer major version to maintain compatibility with current GitHub Actions runtime.",
        "human_impl": "- uses: actions/checkout@v4\n+ uses: actions/checkout@v6",
        "bucket": "polishment"
      },
      {
        "kind": "replace_label_syncer_action",
        "general_idea": "Switch from micnncim/action-label-syncer to brpaz/action-label-syncer, likely due to maintenance status or feature requirements.",
        "human_impl": "- uses: micnncim/action-label-syncer@v1.3.0\n+ uses: brpaz/action-label-syncer@0.2.0",
        "bucket": "polishment"
      }
    ],
    ".github/workflows/update-dependencies-graph.yml": [
      {
        "kind": "bump_github_action_checkout",
        "general_idea": "Update the checkout action to a newer major version to ensure compatibility and access to latest features.",
        "human_impl": "uses: actions/checkout@v6",
        "bucket": "polishment"
      },
      {
        "kind": "bump_github_action_setup_java",
        "general_idea": "Update the setup-java action to a newer major version.",
        "human_impl": "uses: actions/setup-java@v5",
        "bucket": "polishment"
      },
      {
        "kind": "bump_jdk_version",
        "general_idea": "Upgrade the CI environment to use JDK 25 instead of JDK 21.",
        "human_impl": "java-version: '25'",
        "bucket": "polishment"
      },
      {
        "kind": "bump_maven_version",
        "general_idea": "Update the Maven version used in the CI pipeline to a newer patch release.",
        "human_impl": "maven-version: 3.9.11",
        "bucket": "polishment"
      },
      {
        "kind": "add_git_pull",
        "general_idea": "Ensure the working directory is up-to-date with the remote before committing changes to avoid conflicts.",
        "human_impl": "git pull",
        "bucket": "polishment"
      }
    ],
    "doc/dependency-graph.puml": [
      {
        "kind": "bump_dependency_version",
        "general_idea": "Update codingstyle-pom version to 5.43.0-SNAPSHOT in the dependency graph documentation.",
        "human_impl": "rectangle \"codingstyle-pom\\n\\n5.43.0-SNAPSHOT\"",
        "bucket": "polishment"
      },
      {
        "kind": "bump_dependency_version",
        "general_idea": "Update codingstyle version to 5.27.0 in the dependency graph documentation.",
        "human_impl": "rectangle \"codingstyle\\n\\n5.27.0\"",
        "bucket": "polishment"
      },
      {
        "kind": "bump_dependency_version",
        "general_idea": "Update spotbugs-annotations version to 4.9.8 in the dependency graph documentation.",
        "human_impl": "rectangle \"spotbugs-annotations\\n\\n4.9.8\"",
        "bucket": "polishment"
      },
      {
        "kind": "add_dependency",
        "general_idea": "Add jsr305 version 3.0.2 to the dependency graph documentation.",
        "human_impl": "rectangle \"jsr305\\n\\n3.0.2\" as com_google_code_findbugs_jsr305_jar",
        "bucket": "polishment"
      },
      {
        "kind": "bump_dependency_version",
        "general_idea": "Update error_prone_annotations version to 2.46.0 in the dependency graph documentation.",
        "human_impl": "rectangle \"error_prone_annotations\\n\\n2.46.0\"",
        "bucket": "polishment"
      },
      {
        "kind": "bump_dependency_version",
        "general_idea": "Update commons-lang3 version to 3.20.0 in the dependency graph documentation.",
        "human_impl": "rectangle \"commons-lang3\\n\\n3.20.0\"",
        "bucket": "polishment"
      },
      {
        "kind": "bump_dependency_version",
        "general_idea": "Update commons-io version to 2.21.0 in the dependency graph documentation.",
        "human_impl": "rectangle \"commons-io\\n\\n2.21.0\"",
        "bucket": "polishment"
      },
      {
        "kind": "bump_dependency_version",
        "general_idea": "Update streamex version to 0.8.4 in the dependency graph documentation.",
        "human_impl": "rectangle \"streamex\\n\\n0.8.4\"",
        "bucket": "polishment"
      },
      {
        "kind": "add_dependency_link",
        "general_idea": "Add dependency link from spotbugs-annotations to jsr305 in the dependency graph documentation.",
        "human_impl": "com_github_spotbugs_spotbugs_annotations_jar -[#000000]-> com_google_code_findbugs_jsr305_jar",
        "bucket": "polishment"
      }
    ]
  }
}