{
  "meta": {
    "repo": "camunda/connector-template-inbound",
    "stage": "J11->J17",
    "family": null,
    "sha_from": "fb703a1e221338971fb0a1dc5c32e4f70e3cc137",
    "sha_to": "877ce767429f472805027722c83c5c075f821d90"
  },
  "by_file": {
    "pom.xml": [
      {
        "kind": "jdk_version_upgrade",
        "general_idea": "Update the Maven compiler release property to target Java 17 instead of Java 11.",
        "human_impl": "<maven.compiler.release>17</maven.compiler.release>",
        "bucket": "breaking"
      }
    ],
    ".github/workflows/CI.yaml": [
      {
        "kind": "update_ci_java_version",
        "general_idea": "Update the CI workflow to use Java 17 instead of Java 11 to align with the target runtime environment.",
        "human_impl": "java-version: '17'",
        "bucket": "breaking"
      }
    ]
  }
}