{
  "meta": {
    "repo": "Osireg17/Telemetry-Aware-URL-Shortener",
    "stage": "J11->J21",
    "family": null,
    "sha_from": "9a1d3b79662db6fac5e9383ede95210b58bceb1d",
    "sha_to": "74b79025d9a669c67340456f6ad063392de71b9f"
  },
  "by_file": {
    "dependency-reduced-pom.xml": [
      {
        "kind": "update_compiler_config",
        "general_idea": "Switch maven-compiler-plugin configuration from explicit source/target to the unified release flag for better JDK version alignment.",
        "human_impl": "<release>${maven.compiler.release}</release>",
        "bucket": "breaking"
      },
      {
        "kind": "set_jdk_21_properties",
        "general_idea": "Define Maven properties to target JDK 21 for compilation and release.",
        "human_impl": "<maven.compiler.release>21</maven.compiler.release> <maven.compiler.target>21</maven.compiler.target> <maven.compiler.source>21</maven.compiler.source>",
        "bucket": "breaking"
      }
    ],
    "pom.xml": [
      {
        "kind": "set_jdk_version",
        "general_idea": "Update Maven compiler properties and plugin configuration to target Java 21.",
        "human_impl": "<maven.compiler.release>21</maven.compiler.release>",
        "bucket": "breaking"
      }
    ],
    "config.yml": [
      {
        "kind": "switch_db_driver",
        "general_idea": "Changed the database driver class from H2 in-memory to MySQL Connector/J.",
        "human_impl": "-  driverClass: org.h2.Driver\n+  driverClass: com.mysql.cj.jdbc.Driver",
        "bucket": "breaking"
      },
      {
        "kind": "update_db_url",
        "general_idea": "Updated the JDBC connection URL to point to a local MySQL instance with specific SSL and timezone parameters.",
        "human_impl": "-  url: jdbc:h2:mem:urlshortener;DB_CLOSE_DELAY=-1;DB_CLOSE_ON_EXIT=FALSE\n+  url: jdbc:mysql://localhost:3306/urlshortener?useSSL=false&serverTimezone=UTC&allowPublicKeyRetrieval=true",
        "bucket": "breaking"
      },
      {
        "kind": "update_db_credentials",
        "general_idea": "Set specific username and password for the MySQL database connection.",
        "human_impl": "-  user: sa\n-  password:\n+  user: urlshortener_user\n+  password: userpass123",
        "bucket": "breaking"
      }
    ]
  }
}