{
  "meta": {
    "repo": "Krrithen/Distributed-ECommerce-Microservices",
    "stage": "J11->J21",
    "family": "spring-boot-2",
    "sha_from": "e7014ef373656e52d8606c96998470b59d39eb6d",
    "sha_to": "a7519a11ad0fcbb22db17085bfd7fd8a62655934"
  },
  "by_file": {
    "services/api-gateway/pom.xml": [
      {
        "kind": "bump_parent_version",
        "general_idea": "Upgrade Spring Boot parent from 2.7.18 to 3.3.6 to align with Java 21 and Spring Boot 3 ecosystem.",
        "human_impl": "<version>3.3.6</version>",
        "bucket": "breaking"
      },
      {
        "kind": "update_java_version_property",
        "general_idea": "Set the target Java version property to 21 to enable compilation for the new JDK.",
        "human_impl": "<java.version>21</java.version>",
        "bucket": "breaking"
      },
      {
        "kind": "update_spring_cloud_version",
        "general_idea": "Update Spring Cloud version to 2023.0.3 to be compatible with Spring Boot 3.",
        "human_impl": "<spring-cloud.version>2023.0.3</spring-cloud.version>",
        "bucket": "breaking"
      },
      {
        "kind": "update_springdoc_dependency",
        "general_idea": "Replace springdoc-openapi-ui with springdoc-openapi-starter-webmvc-ui to support Spring Boot 3.",
        "human_impl": "<artifactId>springdoc-openapi-starter-webmvc-ui</artifactId>",
        "bucket": "breaking"
      },
      {
        "kind": "add_javax_annotation_api",
        "general_idea": "Add javax.annotation-api to resolve missing annotations removed from Java 11+ module system.",
        "human_impl": "<artifactId>javax.annotation-api</artifactId>",
        "bucket": "breaking"
      }
    ],
    "services/order-service/pom.xml": [
      {
        "kind": "bump_spring_boot_version",
        "general_idea": "Upgrade Spring Boot parent from 2.7.18 to 3.3.6 to align with Java 21 and modern Spring ecosystem.",
        "human_impl": "<version>3.3.6</version>",
        "bucket": "breaking"
      },
      {
        "kind": "set_java_version_property",
        "general_idea": "Update the Java version property from 11 to 21 to reflect the target runtime.",
        "human_impl": "<java.version>21</java.version>",
        "bucket": "breaking"
      },
      {
        "kind": "bump_spring_cloud_version",
        "general_idea": "Upgrade Spring Cloud version to 2023.0.3 to be compatible with Spring Boot 3.x.",
        "human_impl": "<spring-cloud.version>2023.0.3</spring-cloud.version>",
        "bucket": "breaking"
      },
      {
        "kind": "replace_mongodb_with_jpa",
        "general_idea": "Switch data persistence from MongoDB to JPA/SQL by replacing the starter dependency.",
        "human_impl": "<artifactId>spring-boot-starter-data-jpa</artifactId>",
        "bucket": "breaking"
      },
      {
        "kind": "add_postgresql_driver",
        "general_idea": "Add PostgreSQL JDBC driver to support the new JPA data source.",
        "human_impl": "<artifactId>postgresql</artifactId>",
        "bucket": "breaking"
      },
      {
        "kind": "remove_openfeign",
        "general_idea": "Remove Spring Cloud OpenFeign dependency, likely replacing it with gRPC or other mechanisms.",
        "human_impl": "<artifactId>spring-cloud-starter-openfeign</artifactId>",
        "bucket": "breaking"
      },
      {
        "kind": "pin_lombok_version",
        "general_idea": "Explicitly pin Lombok version to 1.18.32 to ensure compatibility with Java 21.",
        "human_impl": "<version>1.18.32</version>",
        "bucket": "breaking"
      },
      {
        "kind": "add_javax_annotation_api",
        "general_idea": "Add javax.annotation-api to replace removed Java EE annotations in Java 11+ (required for gRPC/Lombok compatibility).",
        "human_impl": "<artifactId>javax.annotation-api</artifactId>",
        "bucket": "breaking"
      },
      {
        "kind": "update_compiler_plugin",
        "general_idea": "Update maven-compiler-plugin to version 3.13.0 and set source/target to 21.",
        "human_impl": "<version>3.13.0</version> ... <source>21</source>",
        "bucket": "breaking"
      },
      {
        "kind": "configure_lombok_processor",
        "general_idea": "Configure Lombok as an annotation processor in the compiler plugin to ensure proper code generation.",
        "human_impl": "<annotationProcessorPaths> ... <artifactId>lombok</artifactId> ... </annotationProcessorPaths>",
        "bucket": "breaking"
      }
    ],
    "services/search-service/pom.xml": [
      {
        "kind": "bump_spring_boot_version",
        "general_idea": "Upgrade Spring Boot parent from 2.7.x to 3.3.x to align with Java 21 and modern Spring ecosystem.",
        "human_impl": "<version>3.3.6</version>",
        "bucket": "breaking"
      },
      {
        "kind": "set_java_version",
        "general_idea": "Update the target Java version property from 11 to 21.",
        "human_impl": "<java.version>21</java.version>",
        "bucket": "breaking"
      },
      {
        "kind": "bump_spring_cloud_version",
        "general_idea": "Upgrade Spring Cloud version to 2023.0.3 (Leyton) to be compatible with Spring Boot 3.",
        "human_impl": "<spring-cloud.version>2023.0.3</spring-cloud.version>",
        "bucket": "breaking"
      },
      {
        "kind": "replace_solr_with_elasticsearch",
        "general_idea": "Replace the Solr client dependency with Spring Data Elasticsearch starter.",
        "human_impl": "<artifactId>spring-boot-starter-data-elasticsearch</artifactId>",
        "bucket": "breaking"
      },
      {
        "kind": "remove_springfox",
        "general_idea": "Remove deprecated Springfox Swagger dependencies which are incompatible with Spring Boot 3.",
        "human_impl": "- <artifactId>springfox-boot-starter</artifactId>",
        "bucket": "breaking"
      },
      {
        "kind": "add_javax_annotation",
        "general_idea": "Add javax.annotation-api to replace annotations removed from the JDK in Java 11+ and often required by legacy libraries or gRPC.",
        "human_impl": "<artifactId>javax.annotation-api</artifactId>",
        "bucket": "breaking"
      }
    ]
  }
}