{
  "meta": {
    "repo": "a-oleynik/junit-workshop",
    "stage": "J11->J17",
    "family": "junit4-mockito",
    "sha_from": "db1d6befd3aab927ae7e228cefda69ea496c93f3",
    "sha_to": "c6955a618156caa35f2f5f8f065c65efcd278471"
  },
  "by_file": {
    "pom.xml": [
      {
        "kind": "bump_java_version",
        "general_idea": "Update the target Java version property from 11 to 17 to align with the migration goal.",
        "human_impl": "<java.version>17</java.version>",
        "bucket": "breaking"
      },
      {
        "kind": "bump_maven_compiler_plugin",
        "general_idea": "Update Maven Compiler Plugin to a version compatible with Java 17.",
        "human_impl": "<version>3.13.0</version>",
        "bucket": "breaking"
      }
    ]
  }
}